mostpopuler_news/__init__.py
Mostpopular_News_Kompas.com-0.0.5.dist-info/LICENSE
Mostpopular_News_Kompas.com-0.0.5.dist-info/METADATA
Mostpopular_News_Kompas.com-0.0.5.dist-info/WHEEL
Mostpopular_News_Kompas.com-0.0.5.dist-info/top_level.txt
Mostpopular_News_Kompas.com-0.0.5.dist-info/RECORD
