Metadata-Version: 2.1
Name: Mostpopular-News-Kompas.com
Version: 0.0.5
Summary: This package will get the Mostpopular News From Kompas.com
Home-page: https://github.com/Apatheia8/Mostpopular-News-Kompas.com
Author: Deni Rahmawan
Author-email: dapatheia@gmail.com
Classifier: Programming Language :: Python :: 3
Classifier: License :: OSI Approved :: GNU General Public License v3 (GPLv3)
Classifier: Operating System :: OS Independent
Classifier: Development Status :: 5 - Production/Stable
Requires-Python: >=3.6
License-File: LICENSE
